sr/ScenarioRunner.py
sr/__init__.py
sr/__main__.py
scenario_runner-0.0.11.dist-info/LICENSE
scenario_runner-0.0.11.dist-info/METADATA
scenario_runner-0.0.11.dist-info/WHEEL
scenario_runner-0.0.11.dist-info/entry_points.txt
scenario_runner-0.0.11.dist-info/top_level.txt
scenario_runner-0.0.11.dist-info/RECORD
