Metadata-Version: 2.1
Name: scenario-runner
Version: 0.0.11
Summary: A scenario runner written in python
Home-page: https://github.com/theggelund/sr
Author: Thomas Heggelund
Author-email: thomas.heggelund@gmail.com
License: UNKNOWN
Platform: UNKNOWN
Classifier: Programming Language :: Python :: 3
Classifier: License :: OSI Approved :: MIT License
Classifier: Operating System :: OS Independent
Requires-Python: >=3.7
Requires-Dist: PyYAML (>=5.3.1)
